private_rpa/__init__.py
private_rpa/libraries/__init__.py
private_rpa/libraries/cloud/__init__.py
private_rpa/libraries/cloud/pre_defined_functions.py
private_rpa/libraries/common/__init__.py
private_rpa/libraries/common/common_functions.py
private_rpa/libraries/device/__init__.py
private_rpa/libraries/device/execute_powershell_script.py
private_rpa-0.1.2.dist-info/LICENSE.txt
private_rpa-0.1.2.dist-info/METADATA
private_rpa-0.1.2.dist-info/WHEEL
private_rpa-0.1.2.dist-info/top_level.txt
private_rpa-0.1.2.dist-info/RECORD
